{
  "first_seen_at": "2026-05-31T21:17:03Z",
  "id": "creapure",
  "last_seen_at": "2026-05-31T21:17:03Z",
  "latest_mention_id": "2026-05-31:creapure:48346947",
  "mention_ids": [
    "2026-05-31:creapure:48346947"
  ],
  "name": "Creapure",
  "slug": "creapure",
  "summary": "Creapure \u2014 German creatine brand commenters trust for purity.",
  "thing_url": "https://www.creapure.com/en/",
  "times_seen": 1,
  "why_included": "The thread turned into a concrete brand recommendation instead of generic supplement talk."
}
