{
  "evidence": "Commenters compared it with devon.ai and ReviewStack, debated whether local tools beat SaaS, and said they still wanted the code itself more than another AI summary.",
  "hn_url": "https://news.ycombinator.com/item?id=47796818",
  "id": "2026-04-17:stage:47796818",
  "is_repeat": false,
  "issue_id": "2026-04-17",
  "item_id": "stage",
  "rank": 6,
  "seen_at": "2026-04-17T21:19:50Z",
  "source_story_id": "47796818",
  "source_story_title": "Show HN: Stage \u2013 Putting humans back in control of code review"
}
