{
  "evidence": "The author joined the thread, and commenters discussed the 40 MB PDF, Lulu costs, and whether the book\u2019s price point made sense.",
  "hn_url": "https://news.ycombinator.com/item?id=47911013",
  "id": "2026-04-26:free-textbook-on-engineering-thermodynamics:47911013",
  "is_repeat": false,
  "issue_id": "2026-04-26",
  "item_id": "free-textbook-on-engineering-thermodynamics",
  "rank": 9,
  "seen_at": "2026-04-26T21:02:52Z",
  "source_story_id": "47911013",
  "source_story_title": "Show HN: Free textbook on engineering thermodynamics"
}
